R1_Others_Assignment02/Assignment02/CLAA_P5/carry_L_adder.v
module fulladder (input I0,I1,input Cin,output sum,output Cout);

assign sum= I0^ I1 ^ Cin;
assign Cout= ((I0 ^ I1) & Cin) | (I0 & I1);
endmodule

module carry(input [3:0]A,input [3:0]B,input Cin,output[3:0]C);

assign C[0]=(A[0] & B[0]) | (Cin & (A[0] ^ B[0]));
assign C[1]=(A[1] & B[1]) | ((A[1] ^ B[1])&(A[0]&B[0])) | ((A[1] ^ B[1]) & (A[0] ^ B[0]) & Cin); 
assign C[2]=(A[2] & B[2]) | ((A[2] ^ B[2]) & (A[1] & B[1])) | ((A[2] ^ B[2]) & (A[1] ^ B[1]) & (A[0] ^ B[0]) & Cin);
assign C[3]=(A[3] & B[3]) | ((A[3] & B[3]) & (A[2] & B[2]) | ((A[2] ^ B[2]) & (A[1] & B[1])) | ((A[2] ^ B[2]) & (A[1] ^ B[1]) & (A[0] ^ B[0]) & Cin));
endmodule

module carry_lookahead_adder(input [3:0]A,input [3:0]B,input Cin,output[3:0]sum,output Cout);
wire [3:0]C;
wire [3:0]c;
carry c1(A[3:0],B[3:0],Cin,C[3:0]);
fulladder f1(A[0],B[0],Cin,sum[0],c[0]);
fulladder f2(A[1],A[1],C[0],sum[1],c[1]);
fulladder f3(A[2],B[2],C[1],sum[2],c[2]);
fulladder f4(A[3],B[3],C[2],sum[3],c[3]);
assign Cout=C[3];

endmodule

module carry_lookahead_adder_tb;

reg [3:0]A;
reg [3:0]B;
reg Cin;
wire [3:0]sum;
wire Cout;
carry_lookahead_adder ans(A,B,Cin,sum,Cout);
initial begin
$dumpfile ("cla.vcd");
$dumpvars;
A=0;B=0;Cin=0;
#5;
$display("A=%d, B=%d, Cin=%d, Sum=%d, Cout=%d",A,B,Cin,sum,Cout);
A=1;B=1;Cin=0;
#5;
$display("A=%d, B=%d, Cin=%d, Sum=%d, Cout=%d",A,B,Cin,sum,Cout);
A=2;B=2;Cin=0;
#5;
$display("A=%d, B=%d, Cin=%d, Sum=%d, Cout=%d",A,B,Cin,sum,Cout);
A=3;B=3;Cin=0;
#5;
$display("A=%d, B=%d, Cin=%d, Sum=%d, Cout=%d",A,B,Cin,sum,Cout);
A=4;B=4;Cin=0;
#5;
$display("A=%d, B=%d, Cin=%d, Sum=%d, Cout=%d",A,B,Cin,sum,Cout);
A=5;B=5;Cin=0;
#5;
$display("A=%d, B=%d, Cin=%d, Sum=%d, Cout=%d",A,B,Cin,sum,Cout);
A=6;B=6;Cin=0;
#5;
$display("A=%d, B=%d, Cin=%d, Sum=%d, Cout=%d",A,B,Cin,sum,Cout);
A=7;B=10;Cin=0;
#5;
$display("A=%d, B=%d, Cin=%d, Sum=%d, Cout=%d",A,B,Cin,sum,Cout);

A=8;B=8;Cin=0;
#5;
A=9;B=9;Cin=0;
#5;
A=10;B=10;Cin=0;
#5;
A=11;B=11;Cin=0;
#5;
A=12;B=12;Cin=0;
#5;
A=13;B=13;Cin=0;
#5;
A=14;B=14;Cin=0;
#5;
A=15;B=15;Cin=0;
#5;
$finish();
end

endmodule

R1_Others_Assignment02/Assignment02/CLAA_P5/cla.vcd
$date
	Wed Feb 28 22:03:59 2024
$end
$version
	Icarus Verilog
$end
$timescale
	1s
$end
$scope module carry_lookahead_adder_tb $end
$var wire 4 ! sum [3:0] $end
$var wire 1 " Cout $end
$var reg 4 # A [3:0] $end
$var reg 4 $ B [3:0] $end
$var reg 1 % Cin $end
$scope module ans $end
$var wire 4 & A [3:0] $end
$var wire 4 ' B [3:0] $end
$var wire 1 % Cin $end
$var wire 4 ( sum [3:0] $end
$var wire 4 ) c [3:0] $end
$var wire 1 " Cout $end
$var wire 4 * C [3:0] $end
$scope module c1 $end
$var wire 4 + A [3:0] $end
$var wire 4 , B [3:0] $end
$var wire 1 % Cin $end
$var wire 4 - C [3:0] $end
$upscope $end
$scope module f1 $end
$var wire 1 % Cin $end
$var wire 1 . Cout $end
$var wire 1 / I0 $end
$var wire 1 0 I1 $end
$var wire 1 1 sum $end
$upscope $end
$scope module f2 $end
$var wire 1 2 Cin $end
$var wire 1 3 Cout $end
$var wire 1 4 I0 $end
$var wire 1 5 I1 $end
$var wire 1 6 sum $end
$upscope $end
$scope module f3 $end
$var wire 1 7 Cin $end
$var wire 1 8 Cout $end
$var wire 1 9 I0 $end
$var wire 1 : I1 $end
$var wire 1 ; sum $end
$upscope $end
$scope module f4 $end
$var wire 1 < Cin $end
$var wire 1 = Cout $end
$var wire 1 > I0 $end
$var wire 1 ? I1 $end
$var wire 1 @ sum $end
$upscope $end
$upscope $end
$upscope $end
$enddefinitions $end
$comment Show the parameter values. $end
$dumpall
$end
#0
$dumpvars
0@
0?
0>
0=
0<
0;
0:
09
08
07
06
05
04
03
02
01
00
0/
0.
b0 -
b0 ,
b0 +
b0 *
b0 )
b0 (
b0 '
b0 &
0%
b0 $
b0 #
0"
b0 !
$end
#5
b10 !
b10 (
16
12
b1 )
1.
b1 *
b1 -
10
1/
b1 $
b1 '
b1 ,
b1 #
b1 &
b1 +
#10
1;
b100 !
b100 (
06
17
02
0.
b10 )
13
b10 *
b10 -
00
0/
14
15
b10 $
b10 '
b10 ,
b10 #
b10 &
b10 +
#15
b110 !
b110 (
16
12
b11 )
1.
b11 *
b11 -
10
1/
b11 $
b11 '
b11 ,
b11 #
b11 &
b11 +
#20
0;
1@
b1000 !
b1000 (
06
07
1<
02
0.
03
b100 )
18
b100 *
b100 -
00
1:
0/
04
05
19
b100 $
b100 '
b100 ,
b100 #
b100 &
b100 +
#25
b1010 !
b1010 (
16
12
b101 )
1.
b101 *
b101 -
10
1/
b101 $
b101 '
b101 ,
b101 #
b101 &
b101 +
#30
1;
b1100 !
b1100 (
06
17
02
0.
b110 )
13
b110 *
b110 -
00
0/
14
15
b110 $
b110 '
b110 ,
b110 #
b110 &
b110 +
#35
1"
b1110 *
b1110 -
1=
0;
b1110 )
18
0@
b1 !
b1 (
11
0:
1?
1/
b1010 $
b1010 '
b1010 ,
b111 #
b111 &
b111 +
#40
0<
07
08
b1000 *
b1000 -
01
b1000 )
03
0;
b0 !
b0 (
0@
0/
04
05
09
1>
b1000 $
b1000 '
b1000 ,
b1000 #
b1000 &
b1000 +
#45
b10 !
b10 (
16
12
b1001 )
1.
b1001 *
b1001 -
10
1/
b1001 $
b1001 '
b1001 ,
b1001 #
b1001 &
b1001 +
#50
1;
b100 !
b100 (
06
17
02
0.
b1010 )
13
b1010 *
b1010 -
00
0/
14
15
b1010 $
b1010 '
b1010 ,
b1010 #
b1010 &
b1010 +
#55
b110 !
b110 (
16
12
b1011 )
1.
b1011 *
b1011 -
10
1/
b1011 $
b1011 '
b1011 ,
b1011 #
b1011 &
b1011 +
#60
0;
1@
b1000 !
b1000 (
06
07
1<
02
0.
03
b1100 )
18
b1100 *
b1100 -
00
1:
0/
04
05
19
b1100 $
b1100 '
b1100 ,
b1100 #
b1100 &
b1100 +
#65
b1010 !
b1010 (
16
12
b1101 )
1.
b1101 *
b1101 -
10
1/
b1101 $
b1101 '
b1101 ,
b1101 #
b1101 &
b1101 +
#70
1;
b1100 !
b1100 (
06
17
02
0.
b1110 )
13
b1110 *
b1110 -
00
0/
14
15
b1110 $
b1110 '
b1110 ,
b1110 #
b1110 &
b1110 +
#75
b1110 !
b1110 (
16
12
b1111 )
1.
b1111 *
b1111 -
10
1/
b1111 $
b1111 '
b1111 ,
b1111 #
b1111 &
b1111 +
