Assignment 2/Q4_Priority_Encoder/priority_encoder.v
module priority_encoder(input [7:0] data, output reg [2:0] res);
    always @(*) begin
        if (data[7] == 1'b1)
            res <= 7;
        else if (data[6] == 1'b1)
            res <= 6;
        else if (data[5] == 1'b1)
            res <= 5;
        else if (data[4] == 1'b1)
            res <= 4;
        else if (data[3] == 1'b1)
            res <= 3;
        else if (data[2] == 1'b1)
            res <= 2;
        else if (data[1] == 1'b1)
            res <= 1;
        else if (data[0] == 1'b1)
            res <= 0;
    end
endmodule

module priority_encoder_testbench();
    reg [7:0] data;
    wire [2:0] res;
    priority_encoder priority_encoder_inst (data, res);
    initial begin
        $dumpfile("priority_encoder_testbench.vcd");
        $dumpvars(0, priority_encoder_testbench);
        data = 8'b00000001; #10;
        $display("data = %b, res = %b", data, res);
        data = 8'b00000011; #10;
        $display("data = %b, res = %b", data, res);
        data = 8'b00000101; #10;
        $display("data = %b, res = %b", data, res);
        data = 8'b00001101; #10;
        $display("data = %b, res = %b", data, res);
        data = 8'b00010100; #10;
        $display("data = %b, res = %b", data, res);
        data = 8'b00111010; #10;
        $display("data = %b, res = %b", data, res);
        data = 8'b01100010; #10;
        $display("data = %b, res = %b", data, res);
        data = 8'b11111111; #10;
        $display("data = %b, res = %b", data, res);
        $finish;
    end
endmodule

Assignment 2/Q4_Priority_Encoder/priority_encoder_testbench.vcd
$date
	Wed Apr 10 20:48:31 2024
$end
$version
	Icarus Verilog
$end
$timescale
	1s
$end
$scope module priority_encoder_testbench $end
$var wire 3 ! res [2:0] $end
$var reg 8 " data [7:0] $end
$scope module priority_encoder_inst $end
$var wire 8 # data [7:0] $end
$var reg 3 $ res [2:0] $end
$upscope $end
$upscope $end
$enddefinitions $end
$comment Show the parameter values. $end
$dumpall
$end
#0
$dumpvars
b0 $
b1 #
b1 "
b0 !
$end
#10
b1 !
b1 $
b11 "
b11 #
#20
b10 !
b10 $
b101 "
b101 #
#30
b11 !
b11 $
b1101 "
b1101 #
#40
b100 !
b100 $
b10100 "
b10100 #
#50
b101 !
b101 $
b111010 "
b111010 #
#60
b110 !
b110 $
b1100010 "
b1100010 #
#70
b111 !
b111 $
b11111111 "
b11111111 #
