R1_Others_Assignment02/Assignment02/8to3_priority_encoder_P4/8to3_priority_encoder.v
module priority_encoder(input [7:0]A,output [2:0] out);
    reg out;
  always @(*) begin
    if (A[7]) begin
      out <= 3'b111;
    end else if (A[6]) begin
      out <= 3'b110;
    end else if (A[5]) begin
      out <= 3'b101;
    end else if (A[4]) begin
      out <= 3'b100;
    end else if (A[3]) begin
      out <= 3'b011;
    end else if (A[2]) begin
      out <= 3'b010;
    end else if (A[1]) begin
      out <= 3'b001;
    end else begin
      out <= 3'b000;
    end
  end

endmodule


module priority_encoder_tb;

reg [7:0]A;
wire [2:0]out;
priority_encoder ans(A,out);
initial begin
$dumpfile ("priority_encoder.vcd");
$dumpvars;
A=1;
#5;
$display("A=%d, Out=%d",A,out);
A=2;
#5;
$display("A=%d, Out=%d",A,out);
A=4;
#5;
$display("A=%d, Out=%d",A,out);
A=8;
#5;
$display("A=%d, Out=%d",A,out);
A=16;
#5;
$display("A=%d, Out=%d",A,out);
A=32;
#5;
$display("A=%d, Out=%d",A,out);
A=64;
#5;
$display("A=%d, Out=%d",A,out);
A=130;
#5;
$display("A=%d, Out=%d",A,out);
$finish();
end

endmodule

R1_Others_Assignment02/Assignment02/8to3_priority_encoder_P4/priority_encoder.vcd
$date
	Wed Feb 28 22:02:32 2024
$end
$version
	Icarus Verilog
$end
$timescale
	1s
$end
$scope module priority_encoder_tb $end
$var wire 3 ! out [2:0] $end
$var reg 8 " A [7:0] $end
$scope module ans $end
$var wire 8 # A [7:0] $end
$var reg 3 $ out [2:0] $end
$upscope $end
$upscope $end
$enddefinitions $end
$comment Show the parameter values. $end
$dumpall
$end
#0
$dumpvars
b0 $
b1 #
b1 "
b0 !
$end
#5
b1 !
b1 $
b10 "
b10 #
#10
b10 !
b10 $
b100 "
b100 #
#15
b11 !
b11 $
b1000 "
b1000 #
#20
b100 !
b100 $
b10000 "
b10000 #
#25
b101 !
b101 $
b100000 "
b100000 #
#30
b110 !
b110 $
b1000000 "
b1000000 #
#35
b111 !
b111 $
b10000010 "
b10000010 #
