Assignment 3/Q4_GreyCodeCounter/GreyCodeDownCounter.v
module counter_down(input CLK, RST, UP, output reg [2:0] Q);
    reg [2:0] Q_bin;
    always @(posedge CLK) begin
        if (RST) begin
            Q_bin <= 0;
            Q <= 0;
        end else begin
            if (Q_bin >= 3'b000) begin
                if (UP)
                    Q_bin = Q_bin - 1;
                else
                    Q_bin = Q_bin;
            end else begin
                if (UP)
                    Q_bin = 3'b111;
            end
            Q[0] <= Q_bin[0] ^ Q_bin[1];
            Q[1] <= Q_bin[1] ^ Q_bin[2];
            Q[2] <= Q_bin[2];
        end
        
    end
endmodule

module CounterDOWN_tb;
    reg CLK, RST, UP;
    wire [2:0] Q;
    integer clk_pulse; // For generating the clockpulse
    counter_down counter_inst (CLK, RST, UP, Q);
    initial begin
        $dumpfile("CounterDOWN_tb.vcd");
        $dumpvars(0, CounterDOWN_tb);
        $display("RST UP CLK   | Count");
        $monitor(" %b  %b   %b    | %b", RST, UP, CLK, Q);
        // RST = 1 -> Q value will be reset to 0
        // RST = 0 -> Q value will be set according to logic
        RST = 0; UP = 1; #25
        RST = 0; UP = 0; #2
        RST = 1; UP = 1; #3
        $finish;
    end
    initial begin
        CLK = 1;
        for(clk_pulse = 0; clk_pulse < 34; clk_pulse = clk_pulse + 1) begin
            #1 CLK = ~CLK;
        end
    end
endmodule

Assignment 3/Q4_GreyCodeCounter/CounterDOWN_tb.vcd
$date
	Sat Apr 20 14:30:49 2024
$end
$version
	Icarus Verilog
$end
$timescale
	1s
$end
$scope module CounterDOWN_tb $end
$var wire 3 ! Q [2:0] $end
$var reg 1 " CLK $end
$var reg 1 # RST $end
$var reg 1 $ UP $end
$var integer 32 % clk_pulse [31:0] $end
$scope module counter_inst $end
$var wire 1 " CLK $end
$var wire 1 # RST $end
$var wire 1 $ UP $end
$var reg 3 & Q [2:0] $end
$var reg 3 ' Q_bin [2:0] $end
$upscope $end
$upscope $end
$enddefinitions $end
$comment Show the parameter values. $end
$dumpall
$end
#0
$dumpvars
b111 '
b100 &
b0 %
1$
0#
1"
b100 !
$end
#1
b1 %
0"
#2
b101 !
b101 &
b110 '
b10 %
1"
#3
b11 %
0"
#4
b111 !
b111 &
b101 '
b100 %
1"
#5
b101 %
0"
#6
b110 !
b110 &
b100 '
b110 %
1"
#7
b111 %
0"
#8
b10 !
b10 &
b11 '
b1000 %
1"
#9
b1001 %
0"
#10
b11 !
b11 &
b10 '
b1010 %
1"
#11
b1011 %
0"
#12
b1 !
b1 &
b1 '
b1100 %
1"
#13
b1101 %
0"
#14
b0 !
b0 &
b0 '
b1110 %
1"
#15
b1111 %
0"
#16
b100 !
b100 &
b111 '
b10000 %
1"
#17
b10001 %
0"
#18
b101 !
b101 &
b110 '
b10010 %
1"
#19
b10011 %
0"
#20
b111 !
b111 &
b101 '
b10100 %
1"
#21
b10101 %
0"
#22
b110 !
b110 &
b100 '
b10110 %
1"
#23
b10111 %
0"
#24
b10 !
b10 &
b11 '
b11000 %
1"
#25
b11001 %
0"
0$
#26
b11010 %
1"
#27
b11011 %
0"
1$
1#
#28
b0 !
b0 &
b0 '
b11100 %
1"
#29
b11101 %
0"
#30
b11110 %
1"
