R1_Others_Assignment02/Assignment02/encoder_decoder_P2/2to4_decoder.v
module decoder(input[1:0]A,input E,output [3:0]out);

assign out[3]= E & A[1] & A[0];
assign out[2]= E & A[1] & ~A[0];
assign out[1]= E & ~A[1] & A[0];
assign out[0]= E & ~A[1] & ~A[0];
endmodule


module decoder_tb;
reg [1:0]A;
reg E;
wire[3:0]out;
decoder ans(A,E,out);
initial begin
    $dumpfile("decoder.vcd");
    $dumpvars;
    E=1;
    A=0;
    #5;
    $display("A=%d, E=%d, Out=%d",A,E,out);
    E=1;
    A=1;
    #5;
    $display("A=%d, E=%d, Out=%d",A,E,out);
    E=1;
    A=2;
    #5;
    $display("A=%d, E=%d, Out=%d",A,E,out);
    E=1;
    A=3;
    #5;
    $display("A=%d, E=%d, Out=%d",A,E,out);
    E=0;
    A=0;
    #5;
    $display("A=%d, E=%d, Out=%d",A,E,out);
    E=0;
    A=1;
    #5;
    $display("A=%d, E=%d, Out=%d",A,E,out);
    E=0;
    A=2;
    #5;
    $display("A=%d, E=%d, Out=%d",A,E,out);
    E=0;
    A=3;
    #5;
    $display("A=%d, E=%d, Out=%d",A,E,out);
    $finish();
end

endmodule

R1_Others_Assignment02/Assignment02/encoder_decoder_P2/decoder.vcd
$date
	Wed Feb 28 22:07:40 2024
$end
$version
	Icarus Verilog
$end
$timescale
	1s
$end
$scope module decoder_tb $end
$var wire 4 ! out [3:0] $end
$var reg 2 " A [1:0] $end
$var reg 1 # E $end
$scope module ans $end
$var wire 2 $ A [1:0] $end
$var wire 1 # E $end
$var wire 4 % out [3:0] $end
$upscope $end
$upscope $end
$enddefinitions $end
$comment Show the parameter values. $end
$dumpall
$end
#0
$dumpvars
b1 %
b0 $
1#
b0 "
b1 !
$end
#5
b10 !
b10 %
b1 "
b1 $
#10
b100 !
b100 %
b10 "
b10 $
#15
b1000 !
b1000 %
b11 "
b11 $
#20
b0 !
b0 %
b0 "
b0 $
0#
#25
b1 "
b1 $
#30
b10 "
b10 $
#35
b11 "
b11 $
