Assignment 4/Q1_Moore_Machine/Moore_Machine.v
module mooreFSM(input CLK, RST, A, B, output reg out);
    localparam S0 = 1,
               S1 = 2,
               S2 = 3;

    reg [1:0] CurrentState;
    reg [1:0] NextState;

    always @(posedge CLK) begin
        if(RST)
            CurrentState <= S0;
        else
            CurrentState <= NextState;
    end

    always @(*) begin
        case(CurrentState)
        S0:
            begin
                if(A) NextState <= S1;
                else if(!A) NextState <= S0;
                else NextState <= 2'bzz;
            end
        S1:
            begin
                if(B) NextState <= S2;
                else if(!B) NextState <= S0;
                else NextState <= 2'bzz;
            end
        S2:  
            begin
                if(A | !A | B | !B) NextState <= S0;
                else NextState <= 2'bzz;
            end
        endcase
    end

    always @(*) begin
        if (CurrentState == S2)
            out <= 1;
        else if(CurrentState == S1 | CurrentState == S0) out <= 0;
        else out <= 1'bz;
    end
endmodule

module mooreFSM_testbench;
    reg clk, A, B, reset;
    wire out;
    mooreFSM M(clk, reset, A, B, out);
    always #2 clk = ~clk;

    initial begin
        $dumpfile("mooreFSM.vcd");
        $dumpvars;

        reset = 1; clk = 0; #4
        $display("CLK = %b, Reset = %b, A = %b, B = %b, Out = %b", clk, reset, A, B, out);
        reset = 0;
        A = 1; B = 1'bz; #4;
        $display("CLK = %b, Reset = %b, A = %b, B = %b, Out = %b", clk, reset, A, B, out);
        A = 1'bz; B = 1; #4;
        $display("CLK = %b, Reset = %b, A = %b, B = %b, Out = %b", clk, reset, A, B, out);
        A = 1; B = 0; #4;
        $display("CLK = %b, Reset = %b, A = %b, B = %b, Out = %b", clk, reset, A, B, out);
        A = 0; B = 0; #4;
        $display("CLK = %b, Reset = %b, A = %b, B = %b, Out = %b", clk, reset, A, B, out);
        A = 1; B = 1; #4;
        $display("CLK = %b, Reset = %b, A = %b, B = %b, Out = %b", clk, reset, A, B, out);
        A = 0; B = 1; #4;
        $display("CLK = %b, Reset = %b, A = %b, B = %b, Out = %b", clk, reset, A, B, out);
        A = 1; B = 0; #4;
        $display("CLK = %b, Reset = %b, A = %b, B = %b, Out = %b", clk, reset, A, B, out);
        $finish;
    end
endmodule

Assignment 4/Q1_Moore_Machine/mooreFSM.vcd
$date
	Tue Apr 30 17:28:58 2024
$end
$version
	Icarus Verilog
$end
$timescale
	1s
$end
$scope module mooreFSM_testbench $end
$var wire 1 ! out $end
$var reg 1 " A $end
$var reg 1 # B $end
$var reg 1 $ clk $end
$var reg 1 % reset $end
$scope module M $end
$var wire 1 " A $end
$var wire 1 # B $end
$var wire 1 $ CLK $end
$var wire 1 % RST $end
$var parameter 32 & S0 $end
$var parameter 32 ' S1 $end
$var parameter 32 ( S2 $end
$var reg 2 ) CurrentState [1:0] $end
$var reg 2 * NextState [1:0] $end
$var reg 1 ! out $end
$upscope $end
$upscope $end
$enddefinitions $end
$comment Show the parameter values. $end
$dumpall
b11 (
b10 '
b1 &
$end
#0
$dumpvars
bx *
bx )
1%
0$
x#
x"
x!
$end
#2
0!
bz *
b1 )
1$
#4
b10 *
0$
z#
1"
0%
#6
bz *
b10 )
1$
#8
b11 *
0$
1#
z"
#10
1!
b1 *
b11 )
1$
#12
0$
0#
1"
#14
0!
b10 *
b1 )
1$
#16
b1 *
0$
0"
#18
1$
#20
b10 *
0$
1#
1"
#22
b11 *
b10 )
1$
#24
0$
0"
#26
1!
b1 *
b11 )
1$
#28
0$
0#
1"
#30
0!
b10 *
b1 )
1$
