Assignment 2/Q2_Encoder_Decoder/Enc_Dec.v
module Encoder4to2 (input [3:0] a, output [1:0] b);
    assign b[0] = a[1] | a[3];
    assign b[1] = a[2] | a[3];
endmodule

module Decoder2to4 (input [1:0] a, output [3:0] b);
    assign b[0] = ~a[0] & ~a[1];
    assign b[1] = a[0] & ~a[1];
    assign b[2] = ~a[0] & a[1];
    assign b[3] = a[0] & a[1];
endmodule

module Encoder4to2_tb();
    reg [3:0] enc_input;
    wire [1:0] enc_output;
    reg [1:0] dec_input;
    wire [3:0] dec_output;

    Encoder4to2 enc (enc_input, enc_output);
    Decoder2to4 dec (dec_input, dec_output);

    initial begin
        $dumpfile("Encoder4to2_tb.vcd");
        $dumpvars(0, Encoder4to2_tb);

        $display("Encoder: ");
        enc_input = 4'b0001; #10;
        $display("input = %b, output = %b", enc_input, enc_output);
        enc_input = 4'b0010; #10;
        $display("input = %b, output = %b", enc_input, enc_output);
        enc_input = 4'b0100; #10;
        $display("input = %b, output = %b", enc_input, enc_output);
        enc_input = 4'b1000; #10;
        $display("input = %b, output = %b", enc_input, enc_output);
        
        $display("Decoder: ");
        dec_input = 2'b00; #10;
        $display("input = %b, output = %b", dec_input, dec_output);
        dec_input = 2'b01; #10;
        $display("input = %b, output = %b", dec_input, dec_output);
        dec_input = 2'b10; #10;
        $display("input = %b, output = %b", dec_input, dec_output);
        dec_input = 2'b11; #10;
        $display("input = %b, output = %b", dec_input, dec_output);
        $finish;
    end
endmodule

Assignment 2/Q2_Encoder_Decoder/Encoder4to2_tb.vcd
$date
	Thu Mar 14 14:41:33 2024
$end
$version
	Icarus Verilog
$end
$timescale
	1s
$end
$scope module Encoder4to2_tb $end
$var wire 2 ! enc_output [1:0] $end
$var wire 4 " dec_output [3:0] $end
$var reg 2 # dec_input [1:0] $end
$var reg 4 $ enc_input [3:0] $end
$scope module dec $end
$var wire 2 % a [1:0] $end
$var wire 4 & b [3:0] $end
$upscope $end
$scope module enc $end
$var wire 4 ' a [3:0] $end
$var wire 2 ( b [1:0] $end
$upscope $end
$upscope $end
$enddefinitions $end
$comment Show the parameter values. $end
$dumpall
$end
#0
$dumpvars
b0 (
b1 '
bx &
bx %
b1 $
bx #
bx "
b0 !
$end
#10
b1 !
b1 (
b10 $
b10 '
#20
b10 !
b10 (
b100 $
b100 '
#30
b11 !
b11 (
b1000 $
b1000 '
#40
b1 "
b1 &
b0 #
b0 %
#50
b10 "
b10 &
b1 #
b1 %
#60
b100 "
b100 &
b10 #
b10 %
#70
b1000 "
b1000 &
b11 #
b11 %
