Assignment 4/Q2_Melay_Machine/Melay_Machine.v
module melayFSM(input CLK, RST, A, B, output reg out);
    localparam S0 = 0,
               S1 = 1,
               S2 = 2;

    reg [1:0] State;

    always @(posedge CLK) begin
        if(RST)
            State <= S0;
        else begin
            case(State)
            S0:
                begin
                    if(A) begin
                        out <= 0;
                        State <= S1;
                    end
                    else if(!A) begin
                        out <= 0;
                        State <= S0;
                    end
                    else begin
                        out <= 1'bz;
                        State <= 2'bzz;
                    end
                end
            S1:
                begin
                    if(B) begin
                        out <= 0;
                        State <= S2;
                    end
                    else if(!B) begin
                        out <= 0;
                        State <= S0;
                    end
                    else begin
                        out <= 1'bz;
                        State <= 2'bzz;
                    end
                end
            S2:
                begin
                    if(!A | !B) begin
                        out <= 0;
                        State <= S0;
                    end
                    else if(A & B) begin
                        out <= 1;
                        State <= S2;
                    end
                    else begin
                        out <= 1'bz;
                        State <= 2'bzz;
                    end
                end
            default:
                begin
                    out <= 1'bz;
                    State <= 1'bz;
                end
            endcase
        end
    end

endmodule

module melayFSM_testbench;
    reg clk, A, B, reset;
    wire [1:0]CurrentState;
    wire out;
    melayFSM M(clk, reset, A, B, out);
    always #2 clk = ~clk;

    initial begin
        $dumpfile("melayFSM.vcd");
        $dumpvars;

        reset = 1; clk = 0; #4;
        $display("CLK = %b, Reset = %b, A = %b, B = %b, Out = %b", clk, reset, A, B, out);
        reset = 0;
        A = 1; B = 1'bz; #4;
        $display("CLK = %b, Reset = %b, A = %b, B = %b, Out = %b", clk, reset, A, B, out);
        A = 1'bz; B = 1; #4;
        $display("CLK = %b, Reset = %b, A = %b, B = %b, Out = %b", clk, reset, A, B, out);
        A = 1; B = 1; #4;
        $display("CLK = %b, Reset = %b, A = %b, B = %b, Out = %b", clk, reset, A, B, out);
        A = 1; B = 1; #4;
        $display("CLK = %b, Reset = %b, A = %b, B = %b, Out = %b", clk, reset, A, B, out);
        A = 0; B = 1; #4;
        $display("CLK = %b, Reset = %b, A = %b, B = %b, Out = %b", clk, reset, A, B, out);
        A = 1; B = 0; #4;
        $display("CLK = %b, Reset = %b, A = %b, B = %b, Out = %b", clk, reset, A, B, out);
        A = 1'bz; B = 1; #4;
        $display("CLK = %b, Reset = %b, A = %b, B = %b, Out = %b", clk, reset, A, B, out);
        A = 1; B = 1; #4;
        $display("CLK = %b, Reset = %b, A = %b, B = %b, Out = %b", clk, reset, A, B, out);
        $finish;
    end
endmodule

Assignment 4/Q2_Melay_Machine/melayFSM.vcd
$date
	Tue Apr 30 17:29:36 2024
$end
$version
	Icarus Verilog
$end
$timescale
	1s
$end
$scope module melayFSM_testbench $end
$var wire 1 ! out $end
$var reg 1 " A $end
$var reg 1 # B $end
$var reg 1 $ clk $end
$var reg 1 % reset $end
$scope module M $end
$var wire 1 " A $end
$var wire 1 # B $end
$var wire 1 $ CLK $end
$var wire 1 % RST $end
$var parameter 32 & S0 $end
$var parameter 32 ' S1 $end
$var parameter 32 ( S2 $end
$var reg 2 ) State [1:0] $end
$var reg 1 ! out $end
$upscope $end
$upscope $end
$enddefinitions $end
$comment Show the parameter values. $end
$dumpall
b10 (
b1 '
b0 &
$end
#0
$dumpvars
bx )
1%
0$
x#
x"
x!
$end
#2
b0 )
1$
#4
0$
z#
1"
0%
#6
b1 )
0!
1$
#8
0$
1#
z"
#10
b10 )
1$
#12
0$
1"
#14
1!
1$
#16
0$
#18
1$
#20
0$
0"
#22
b0 )
0!
1$
#24
0$
0#
1"
#26
b1 )
1$
#28
0$
1#
z"
#30
b10 )
1$
#32
0$
1"
#34
1!
1$
