Assignment 3/Q6_Memory/Memory.v
module memory(input CLK, input WE, input [6:0] WriteADDR, 
    input [6:0] ReadADDR, input [15:0] input_data, 
    output reg [15:0] output_WriteDATA, output reg [15:0] output_ReadDATA);
    reg [0:15] mem[0:127];

    always @ (posedge CLK) begin
        if (WE) begin
            mem[WriteADDR] = input_data;
            output_WriteDATA = mem[WriteADDR];
        end else
            output_ReadDATA = mem[ReadADDR];
    end
endmodule

module mem_testbench;
    reg CLK, WE;
    reg [6:0] WriteADDR, ReadADDR;
    reg [15:0] input_data;
    wire [15:0] output_WriteDATA, output_ReadDATA;
    integer clk_pulse; // For generating the clockpulse
    memory memory_inst (CLK, WE, WriteADDR, ReadADDR, input_data, output_WriteDATA, output_ReadDATA);
    initial begin
        $dumpfile("memory_tb.vcd");
        $dumpvars(0, mem_testbench);
        $display("WE CLK   | WriteADDR  ReadADDR     input_data      output_WriteDATA   output_ReadDATA");
        #1;
        WE = 1; WriteADDR = 1; input_data = 7; #4;
        WE = 1; WriteADDR = 3; input_data = 10; #4;
        WE = 1; WriteADDR = 127; input_data = 15; #4;
        WE = 1; WriteADDR = 5; input_data = 16'b1111111111111111; #4;
        WE = 0; ReadADDR = 1; #4;
        WE = 0; ReadADDR = 3; #4;
        WE = 0; ReadADDR = 5; #4;
        WE = 0; ReadADDR = 127; #4;
        WE = 0; ReadADDR = 5; #4;
        $finish;
    end
    always @ (negedge CLK) begin
        $display(" %b   %b    | %b   %b   %b   %b   %b", WE, CLK, WriteADDR, ReadADDR, input_data, output_WriteDATA, output_ReadDATA);
    end
    initial begin
        CLK = 0;
        for(clk_pulse = 0; clk_pulse < 18; clk_pulse = clk_pulse + 1) begin
            #2 CLK = ~CLK;
        end
    end
endmodule

Assignment 3/Q6_Memory/memory_tb.vcd
$date
	Sat Apr 20 14:27:46 2024
$end
$version
	Icarus Verilog
$end
$timescale
	1s
$end
$scope module mem_testbench $end
$var wire 16 ! output_WriteDATA [15:0] $end
$var wire 16 " output_ReadDATA [15:0] $end
$var reg 1 # CLK $end
$var reg 7 $ ReadADDR [6:0] $end
$var reg 1 % WE $end
$var reg 7 & WriteADDR [6:0] $end
$var reg 16 ' input_data [15:0] $end
$var integer 32 ( clk_pulse [31:0] $end
$scope module memory_inst $end
$var wire 1 # CLK $end
$var wire 7 ) ReadADDR [6:0] $end
$var wire 1 % WE $end
$var wire 7 * WriteADDR [6:0] $end
$var wire 16 + input_data [15:0] $end
$var reg 16 , output_ReadDATA [15:0] $end
$var reg 16 - output_WriteDATA [15:0] $end
$upscope $end
$upscope $end
$enddefinitions $end
$comment Show the parameter values. $end
$dumpall
$end
#0
$dumpvars
bx -
bx ,
bx +
bx *
bx )
b0 (
bx '
bx &
x%
bx $
0#
bx "
bx !
$end
#1
b111 '
b111 +
b1 &
b1 *
1%
#2
b111 !
b111 -
b1 (
1#
#4
b10 (
0#
#5
b1010 '
b1010 +
b11 &
b11 *
#6
b1010 !
b1010 -
b11 (
1#
#8
b100 (
0#
#9
b1111 '
b1111 +
b1111111 &
b1111111 *
#10
b1111 !
b1111 -
b101 (
1#
#12
b110 (
0#
#13
b1111111111111111 '
b1111111111111111 +
b101 &
b101 *
#14
b1111111111111111 !
b1111111111111111 -
b111 (
1#
#16
b1000 (
0#
#17
b1 $
b1 )
0%
#18
b111 "
b111 ,
b1001 (
1#
#20
b1010 (
0#
#21
b11 $
b11 )
#22
b1010 "
b1010 ,
b1011 (
1#
#24
b1100 (
0#
#25
b101 $
b101 )
#26
b1111111111111111 "
b1111111111111111 ,
b1101 (
1#
#28
b1110 (
0#
#29
b1111111 $
b1111111 )
#30
b1111 "
b1111 ,
b1111 (
1#
#32
b10000 (
0#
#33
b101 $
b101 )
#34
b1111111111111111 "
b1111111111111111 ,
b10001 (
1#
#36
b10010 (
0#
