Assignment 3/Q1_SRLstch/SRLatch.v
module SRLatch (input CLK, S, R, enable, reset, output reg Q, Qbar);
  always @(CLK, enable, reset) begin // Asynchronous Enable and Reset
    if (reset) begin
      Q <= 0;
      Qbar <= 1;
    end else if (enable) begin
      if (S && !R) begin
        Q <= 1;
        Qbar <= 0;
      end else if (!S && R) begin
        Q <= 0;
        Qbar <= 1;
      end else if (S && R) begin
        // Invalid State
        Q <= 0;
        Qbar <= 0;
      end else begin
        // Hold State
        Q <= Q;
        Qbar <= Qbar;
      end
    end
  end
endmodule

module SRLatch_tb;
  reg S, R, En, RST, CLK;
  wire Q, Qbar;
  integer clk_pulse;
  SRLatch SRLatch_inst (CLK, S, R, En, RST, Q, Qbar);
  initial begin
    $dumpfile("SRLatch_tb.vcd");
    $dumpvars(0, SRLatch_tb);
    // RST = 1 -> Q value will be reset to 0
    // RST = 0 -> Q value will be set according to logic
    En = 1; RST = 0;
    S = 0; R = 0;
    #10 $display("CLK=%b, S=%b, R=%b, En=%b, RST=%b, Q=%b, Qbar=%b", CLK, S, R, En, RST, Q, Qbar);
    S = 1; R = 1;
    #10 $display("CLK=%b, S=%b, R=%b, En=%b, RST=%b, Q=%b, Qbar=%b", CLK, S, R, En, RST, Q, Qbar);
    S = 0; R = 1;
    #10 $display("CLK=%b, S=%b, R=%b, En=%b, RST=%b, Q=%b, Qbar=%b", CLK, S, R, En, RST, Q, Qbar);
    S = 1; R = 0;
    #10 $display("CLK=%b, S=%b, R=%b, En=%b, RST=%b, Q=%b, Qbar=%b", CLK, S, R, En, RST, Q, Qbar);
    S = 0; R = 0;
    #10 $display("CLK=%b, S=%b, R=%b, En=%b, RST=%b, Q=%b, Qbar=%b", CLK, S, R, En, RST, Q, Qbar);
    En = 0; RST = 0;
    S = 0; R = 0;
    #10 $display("CLK=%b, S=%b, R=%b, En=%b, RST=%b, Q=%b, Qbar=%b", CLK, S, R, En, RST, Q, Qbar);
    En = 1; RST = 1;
    S = 1; R = 1;
    #10 $display("CLK=%b, S=%b, R=%b, En=%b, RST=%b, Q=%b, Qbar=%b", CLK, S, R, En, RST, Q, Qbar);
    $finish;
   end
   initial begin
      CLK = 1;
      for(clk_pulse = 0; clk_pulse < 8; clk_pulse = clk_pulse + 1) begin
          #10 CLK = ~CLK;
      end
    end
endmodule

Assignment 3/Q1_SRLstch/SRLatch_tb.vcd
$date
	Sat Apr 20 14:30:01 2024
$end
$version
	Icarus Verilog
$end
$timescale
	1s
$end
$scope module SRLatch_tb $end
$var wire 1 ! Qbar $end
$var wire 1 " Q $end
$var reg 1 # CLK $end
$var reg 1 $ En $end
$var reg 1 % R $end
$var reg 1 & RST $end
$var reg 1 ' S $end
$var integer 32 ( clk_pulse [31:0] $end
$scope module SRLatch_inst $end
$var wire 1 # CLK $end
$var wire 1 % R $end
$var wire 1 ' S $end
$var wire 1 $ enable $end
$var wire 1 & reset $end
$var reg 1 " Q $end
$var reg 1 ! Qbar $end
$upscope $end
$upscope $end
$enddefinitions $end
$comment Show the parameter values. $end
$dumpall
$end
#0
$dumpvars
b0 (
0'
0&
0%
1$
1#
x"
x!
$end
#10
0!
0"
b1 (
0#
1%
1'
#20
1!
b10 (
1#
0'
#30
0!
1"
b11 (
0#
0%
1'
#40
b100 (
1#
0'
#50
b101 (
0#
0$
#60
1!
0"
b110 (
1#
1%
1'
1&
1$
#70
b111 (
0#
