Assignment 1/Q4._Adder_Subtractor/Adder_Subtractor.v
module half_adder (input a, input b, output sum, output carry);
    xor gate_sum (sum, a, b);
    and gate_carry (carry, a, b);
endmodule

module full_adder (input a, input b, input carry_in, output sum, output carry_out);
    wire w1, w2, w3;
    half_adder ha1 (a, b, w1, w2);
    half_adder ha2 (w1, carry_in, sum, w3);
    or gate_carry_out (carry_out, w2, w3);
endmodule

module half_subtractor (input a, input b, output difference, output borrow);
    wire not_a;
    xor gate_difference (difference, a, b);
    not gate_a (not_a, a);
    and gate_borrow (borrow, not_a, b);
endmodule

module full_subtractor (input a, input b, input borrow_in, output difference, output borrow_out);
    wire w1, w2, w3;
    half_subtractor hs1 (a, b, w1, w2);
    half_subtractor hs2 (w1, borrow_in, difference, w3);
    or gate_borrow_out (borrow_out, w2, w3);
endmodule

module Adder_Subtractor_TestBench ();
    reg HA1, HA2, FA1, FA2, FA_CARRY_IN, HS1, HS2, FS1, FS2, FS_BORROW_IN;
    wire HA_SUM, HA_CARRY, FA_SUM, FA_CARRY_OUT, HS_DIFF, HS_BORROW, FS_DIFF, FS_BORROW_OUT;
    half_adder ha (HA1, HA2, HA_SUM, HA_CARRY);
    full_adder fa (FA1, FA2, FA_CARRY_IN, FA_SUM, FA_CARRY_OUT);
    half_subtractor hs (HS1, HS2, HS_DIFF, HS_BORROW);
    full_subtractor fs (FS1, FS2, FS_BORROW_IN, FS_DIFF, FS_BORROW_OUT);
    initial begin
        $dumpfile("adder_subtractor_test.vcd");
        $dumpvars(0, Adder_Subtractor_TestBench);

        HA1 = 0; HA2 = 0;
        #10 HA1 = 0; HA2 = 1;
        #10 HA1 = 1; HA2 = 0;
        #10 HA1 = 1; HA2 = 1;

        #20 FA1 = 0; FA2 = 0; FA_CARRY_IN = 0;
        #10 FA1 = 0; FA2 = 1; FA_CARRY_IN = 0;
        #10 FA1 = 1; FA2 = 0; FA_CARRY_IN = 0;
        #10 FA1 = 1; FA2 = 1; FA_CARRY_IN = 0;
        #10 FA1 = 0; FA2 = 0; FA_CARRY_IN = 1;
        #10 FA1 = 0; FA2 = 1; FA_CARRY_IN = 1;
        #10 FA1 = 1; FA2 = 0; FA_CARRY_IN = 1;
        #10 FA1 = 1; FA2 = 1; FA_CARRY_IN = 1;

        #20 HS1 = 0; HS2 = 0;
        #10 HS1 = 0; HS2 = 1;
        #10 HS1 = 1; HS2 = 0;
        #10 HS1 = 1; HS2 = 1;

        #20 FS1 = 0; FS2 = 0; FS_BORROW_IN = 0;
        #10 FS1 = 0; FS2 = 1; FS_BORROW_IN = 0;
        #10 FS1 = 1; FS2 = 0; FS_BORROW_IN = 0;
        #10 FS1 = 1; FS2 = 1; FS_BORROW_IN = 0;
        #10 FS1 = 0; FS2 = 0; FS_BORROW_IN = 1;
        #10 FS1 = 0; FS2 = 1; FS_BORROW_IN = 1;
        #10 FS1 = 1; FS2 = 0; FS_BORROW_IN = 1;
        #10 FS1 = 1; FS2 = 1; FS_BORROW_IN = 1;
        #10 $finish;
    end
endmodule

Assignment 1/Q4._Adder_Subtractor/adder_subtractor_test.vcd
$date
	Sun Feb 18 13:40:38 2024
$end
$version
	Icarus Verilog
$end
$timescale
	1s
$end
$scope module Adder_Subtractor_TestBench $end
$var wire 1 ! HS_DIFF $end
$var wire 1 " HS_BORROW $end
$var wire 1 # HA_SUM $end
$var wire 1 $ HA_CARRY $end
$var wire 1 % FS_DIFF $end
$var wire 1 & FS_BORROW_OUT $end
$var wire 1 ' FA_SUM $end
$var wire 1 ( FA_CARRY_OUT $end
$var reg 1 ) FA1 $end
$var reg 1 * FA2 $end
$var reg 1 + FA_CARRY_IN $end
$var reg 1 , FS1 $end
$var reg 1 - FS2 $end
$var reg 1 . FS_BORROW_IN $end
$var reg 1 / HA1 $end
$var reg 1 0 HA2 $end
$var reg 1 1 HS1 $end
$var reg 1 2 HS2 $end
$scope module fa $end
$var wire 1 ) a $end
$var wire 1 * b $end
$var wire 1 + carry_in $end
$var wire 1 ( carry_out $end
$var wire 1 3 w3 $end
$var wire 1 4 w2 $end
$var wire 1 5 w1 $end
$var wire 1 ' sum $end
$scope module ha1 $end
$var wire 1 ) a $end
$var wire 1 * b $end
$var wire 1 4 carry $end
$var wire 1 5 sum $end
$upscope $end
$scope module ha2 $end
$var wire 1 5 a $end
$var wire 1 + b $end
$var wire 1 3 carry $end
$var wire 1 ' sum $end
$upscope $end
$upscope $end
$scope module fs $end
$var wire 1 , a $end
$var wire 1 - b $end
$var wire 1 . borrow_in $end
$var wire 1 & borrow_out $end
$var wire 1 6 w3 $end
$var wire 1 7 w2 $end
$var wire 1 8 w1 $end
$var wire 1 % difference $end
$scope module hs1 $end
$var wire 1 , a $end
$var wire 1 - b $end
$var wire 1 7 borrow $end
$var wire 1 8 difference $end
$var wire 1 9 not_a $end
$upscope $end
$scope module hs2 $end
$var wire 1 8 a $end
$var wire 1 . b $end
$var wire 1 6 borrow $end
$var wire 1 % difference $end
$var wire 1 : not_a $end
$upscope $end
$upscope $end
$scope module ha $end
$var wire 1 / a $end
$var wire 1 0 b $end
$var wire 1 $ carry $end
$var wire 1 # sum $end
$upscope $end
$scope module hs $end
$var wire 1 1 a $end
$var wire 1 2 b $end
$var wire 1 " borrow $end
$var wire 1 ! difference $end
$var wire 1 ; not_a $end
$upscope $end
$upscope $end
$enddefinitions $end
$comment Show the parameter values. $end
$dumpall
$end
#0
$dumpvars
x;
x:
x9
x8
x7
x6
x5
x4
x3
x2
x1
00
0/
x.
x-
x,
x+
x*
x)
x(
x'
x&
x%
0$
0#
x"
x!
$end
#10
1#
10
#20
00
1/
#30
0#
1$
10
#50
0(
0'
03
05
04
0+
0*
0)
#60
1'
15
1*
#70
0*
1)
#80
0'
1(
05
14
1*
#90
0(
1'
04
1+
0*
0)
#100
1(
0'
13
15
1*
#110
0*
1)
#120
1'
03
05
14
1*
#140
0"
0!
1;
02
01
#150
1!
1"
12
#160
0"
0;
02
11
#170
0!
12
#190
0&
1:
0%
06
07
08
19
0.
0-
0,
#200
1%
0:
1&
18
17
1-
#210
0&
07
09
0-
1,
#220
0%
1:
08
1-
#230
1&
1%
16
19
1.
0-
0,
#240
06
0%
0:
18
17
1-
#250
0&
07
09
0-
1,
#260
1&
16
1%
1:
08
1-
