Assignment 3/Q2_DLatch/ImprovedDLatch.v
// module DLatch(input CLK, RST, D, output reg N1, N2, Q);
//     always @(CLK) begin
//         if (RST)
//             Q <= 0;
//         N1 <= #1 (D & CLK);
//         N2 <= #2 (Q & (~CLK));
//     end
//     always @(N1, N2) begin
//         if (RST)
//             Q = 0;
//         else
//             Q = #1 (N1 | N2);
//     end
// endmodule

module DLatch(input CLK, RST, D, output reg N1, N2, Q);
    reg CLK_n;
    always @(CLK) begin
        if (RST)
            Q <= 0;
        N1 <= #1 (D & CLK);
    end
    always @(CLK) begin
        if (RST)
            Q <= 0;
        else
            CLK_n <= #1 ~CLK;
    end
    always @(Q, CLK_n) begin
        if (RST)
            Q <= 0;
        else
            N2 <= #1 (Q & CLK_n);
    end
    always @(N1, N2) begin
        if (RST)
            Q <= 0;
        else
            Q <= #1 (N1 | N2);
    end
endmodule

module DLatch_tb;
    reg D, CLK, RST;
    wire Q, N1, N2;
    integer clk_pulse;
    DLatch DLatch_inst (CLK, RST, D, N1, N2, Q);
    initial begin
        $dumpfile("DLatch_tb.vcd");
        $dumpvars(0, DLatch_tb);
        // RST = 1 -> Q value will be reset to 0
        // RST = 0 -> Q value will be set according to logic
        RST = 1; #4;
        $display("RST=%b, CLK=%b, D=%b, Q=%b", RST, CLK, D, Q);
        RST = 0;
        D = 0;
        #4 $display("RST=%b, CLK=%b, D=%b, Q=%b", RST, CLK, D, Q);
        D = 1;
        #4 $display("RST=%b, CLK=%b, D=%b, Q=%b", RST, CLK, D, Q);
        D = 1;
        #4 $display("RST=%b, CLK=%b, D=%b, Q=%b", RST, CLK, D, Q);
        D = 0;
        #4 $display("RST=%b, CLK=%b, D=%b, Q=%b", RST, CLK, D, Q);
        D = 1;
        #4 $display("RST=%b, CLK=%b, D=%b, Q=%b", RST, CLK, D, Q);
        D = 1;
        #4 $display("RST=%b, CLK=%b, D=%b, Q=%b", RST, CLK, D, Q);
        D = 0;
        #4 $display("RST=%b, CLK=%b, D=%b, Q=%b", RST, CLK, D, Q);
        D = 1;
        #4 $display("RST=%b, CLK=%b, D=%b, Q=%b", RST, CLK, D, Q);
        $finish;
    end
    initial begin
        CLK = 0;
        for(clk_pulse = 0; clk_pulse < 10; clk_pulse = clk_pulse + 1) begin
            #4 CLK = ~CLK;
        end
    end
endmodule

Assignment 3/Q2_DLatch/DLatch_tb.vcd
$date
	Sat Apr 20 22:44:14 2024
$end
$version
	Icarus Verilog
$end
$timescale
	1s
$end
$scope module DLatch_tb $end
$var wire 1 ! Q $end
$var wire 1 " N2 $end
$var wire 1 # N1 $end
$var reg 1 $ CLK $end
$var reg 1 % D $end
$var reg 1 & RST $end
$var integer 32 ' clk_pulse [31:0] $end
$scope module DLatch_inst $end
$var wire 1 $ CLK $end
$var wire 1 % D $end
$var wire 1 & RST $end
$var reg 1 ( CLK_n $end
$var reg 1 # N1 $end
$var reg 1 " N2 $end
$var reg 1 ! Q $end
$upscope $end
$upscope $end
$enddefinitions $end
$comment Show the parameter values. $end
$dumpall
$end
#0
$dumpvars
x(
b0 '
1&
x%
0$
x#
x"
0!
$end
#1
0#
#4
b1 '
1$
0%
0&
#5
0(
#6
0"
#8
b10 '
0$
1%
#9
1(
#12
b11 '
1$
#13
1#
0(
#14
1!
#16
b100 '
0$
0%
#17
1(
0#
#18
1"
0!
#19
1!
0"
#20
1"
0!
b101 '
1$
1%
#21
1!
0"
1#
0(
#24
b110 '
0$
#25
1(
0#
#26
1"
0!
#27
1!
0"
#28
1"
0!
b111 '
1$
0%
#29
1!
0"
0(
#30
0!
#32
b1000 '
0$
1%
#33
1(
#36
b1001 '
1$
